blender/__init__.py
blender/distutils/__init__.py
blender/distutils/bdist_blender_addon.py
blender.distutils-1.0.5.dist-info/METADATA
blender.distutils-1.0.5.dist-info/RECORD
blender.distutils-1.0.5.dist-info/WHEEL
blender.distutils-1.0.5.dist-info/entry_points.txt
blender.distutils-1.0.5.dist-info/top_level.txt
