Metadata-Version: 2.1
Name: blender.distutils
Version: 1.0.5
Summary: Blender distutils addon
Home-page: https://github.com/charlesfleche/blender.distutils
Author: Charles Flèche
Author-email: charles.fleche@free.fr
License: MIT
Keywords: distutils blender
Platform: UNKNOWN
Classifier: Development Status :: 5 - Production/Stable
Classifier: Intended Audience :: Developers
Classifier: License :: OSI Approved :: MIT License
Classifier: Programming Language :: Python :: 3 :: Only
